vexusproto/__init__.py
vexusproto/e2ee.py
vexusproto-0.2.dist-info/METADATA
vexusproto-0.2.dist-info/WHEEL
vexusproto-0.2.dist-info/top_level.txt
vexusproto-0.2.dist-info/RECORD
